rmcl/__init__.py
rmcl/api.py
rmcl/config.py
rmcl/const.py
rmcl/datacache.py
rmcl/exceptions.py
rmcl/items.py
rmcl/sync.py
rmcl/utils.py
rmcl/zipdir.py
rmcl-0.4.2.dist-info/LICENSE.txt
rmcl-0.4.2.dist-info/WHEEL
rmcl-0.4.2.dist-info/METADATA
rmcl-0.4.2.dist-info/RECORD
