Metadata-Version: 2.1
Name: rmcl
Version: 0.4.2
Summary: reMarkable Cloud Library
Home-page: https://github.com/rschroll/rmcl
License: MIT
Author: Robert Schroll
Author-email: rschroll@gmail.com
Requires-Python: >=3.7,<4.0
Classifier: License :: OSI Approved :: MIT License
Classifier: Programming Language :: Python :: 3
Classifier: Programming Language :: Python :: 3.7
Classifier: Programming Language :: Python :: 3.8
Classifier: Programming Language :: Python :: 3.9
Requires-Dist: asks (>=2.4.12,<3.0.0)
Requires-Dist: trio (>=0.18.0,<0.19.0)
Requires-Dist: xdg (>=5.0.1,<6.0.0)
Project-URL: Repository, https://github.com/rschroll/rmcl
